five_in_row/__init__.py
five_in_row/analysis.py
five_in_row/client.py
five_in_row/model.py
five_in_row/types.py
five_in_row-0.0.2.dist-info/METADATA
five_in_row-0.0.2.dist-info/WHEEL
five_in_row-0.0.2.dist-info/top_level.txt
five_in_row-0.0.2.dist-info/RECORD
