Metadata-Version: 2.1
Name: five-in-row
Version: 0.0.2
Summary: Framework for playing piskvorky.jobs.cz
Home-page: https://github.com/JakubTesarek/five
Author: Jakub Tesárek
Author-email: jakub@tesarek.me
License: GPL-3
Platform: UNKNOWN
Requires-Python: >=3.7
Requires-Dist: requests
Requires-Dist: numpy
Provides-Extra: dev
Requires-Dist: setuptools ; extra == 'dev'
Requires-Dist: wheel ; extra == 'dev'
Requires-Dist: pytest ; extra == 'dev'
Requires-Dist: pytest-cov ; extra == 'dev'
Requires-Dist: pytest-mock ; extra == 'dev'
Requires-Dist: pytest-benchmark ; extra == 'dev'
Requires-Dist: requests-mock ; extra == 'dev'
Requires-Dist: mypy ; extra == 'dev'
Requires-Dist: flake8 ; extra == 'dev'
Requires-Dist: flake8-colors ; extra == 'dev'
Requires-Dist: flake8-eradicate ; extra == 'dev'
Requires-Dist: flake8-print ; extra == 'dev'
Requires-Dist: flake8-todo ; extra == 'dev'
Requires-Dist: twine ; extra == 'dev'
